{
    "title": "Tools",
    "content":[{
        "label": "ucm",
        "path":"../../assets/images/ucm.png"
    },
    {
        "label": "cmit",
        "path":"../../assets/images/cmit.png"
    },
    {
        "label": "win",
        "path":"../../assets/images/win.png"
    },
    {
        "label": "spectrum-loc",
        "path":"../../assets/images/spectrum-store.png"
    },
    {
        "label": "spectrum-navigator",
        "path":"../../assets/images/spectrum-navigator.png"
    },
    {
        "label": "channel-lineup",
        "path":"../../assets/images/channel-lineup.png"
    },
    {
        "label": "spectrum-emulator",
        "path":"../../assets/images/spectrum-emulator.png"
    },
    {
        "label": "phone-tools",
        "path":"../../assets/images/phone-tools.png"
    },
    {
        "label": "spectrum-com",
        "path":"../../assets/images/spectrum-com.png"
    },
    {
        "label": "scope",
        "path":"../../assets/images/scope.png"
    },
    {
        "label": "spectrum-telescope",
        "path":"../../assets/images/spectrum-telescope.png"
    },
    {
        "label": "cobrowse",
        "path":"../../assets/images/cobrowse.png"
    },
    {
        "label": "sat",
        "path":"../../assets/images/sat.png"
    },
    {
        "label": "agreement-initiator",
        "path":"../../assets/images/agreement-initiator.png"
    },
    {
        "label": "tech-tracker",
        "path":"../../assets/images/tech-tracker.png"
    },
    {
        "label": "copilot",
        "path":"../../assets/images/copilot.png"
    },
    {
        "label": "verbatim",
        "path":"../../assets/images/verbatim.png"
    },
    {
        "label": "meta-view",
        "path":"../../assets/images/meta-view.png"
    },
    {
        "label": "cable-mover",
        "path":"../../assets/images/cable-mover.png"
    },
    {
        "label": "spectrum-wifi",
        "path":"../../assets/images/spectrum-wifi.png"
    },
    {
        "label": "tms",
        "path":"../../assets/images/tms.png"
    },
    {
        "label": "uim",
        "path":"../../assets/images/uim.png"
    },
    {
        "label": "usps",
        "path":"../../assets/images/usps.png"
    },
    {
        "label": "wfm-portal",
        "path":"../../assets/images/wfm-portal.png"
    },
    {
        "label": "go2-broadband",
        "path":"../../assets/images/go2-broadband.png"
    },
    {
        "label": "emulator-virtual",
        "path":"../../assets/images/emulator-virtual.png"
    },
    {
        "label": "customer-selfcare",
        "path":"../../assets/images/customer-selfcare.png"
    },
    {
        "label": "my-spectrum",
        "path":"../../assets/images/my-spectrum.png"
    }
]
}